discourseflow/__init__.py
discourseflow/cli.py
discourseflow/discourseflow.py
discourseflow-0.1.0.dist-info/AUTHORS.rst
discourseflow-0.1.0.dist-info/LICENSE
discourseflow-0.1.0.dist-info/METADATA
discourseflow-0.1.0.dist-info/WHEEL
discourseflow-0.1.0.dist-info/entry_points.txt
discourseflow-0.1.0.dist-info/top_level.txt
discourseflow-0.1.0.dist-info/RECORD
